rest_aiohttp-1.0.1.dist-info/DESCRIPTION.rst
rest_aiohttp-1.0.1.dist-info/METADATA
rest_aiohttp-1.0.1.dist-info/RECORD
rest_aiohttp-1.0.1.dist-info/WHEEL
rest_aiohttp-1.0.1.dist-info/metadata.json
rest_aiohttp-1.0.1.dist-info/top_level.txt
restaiohttp/__init__.py
restaiohttp/__main__.py
restaiohttp/serializers.py
